SungrowModbusTcpClient/SungrowModbusTcpClient.py
SungrowModbusTcpClient/__init__.py
SungrowModbusTcpClient-0.1.6.dist-info/LICENSE
SungrowModbusTcpClient-0.1.6.dist-info/METADATA
SungrowModbusTcpClient-0.1.6.dist-info/WHEEL
SungrowModbusTcpClient-0.1.6.dist-info/top_level.txt
SungrowModbusTcpClient-0.1.6.dist-info/RECORD
